trina_extension/__init__.py
trina_extension/extension.py
trina_extension-1.0.0.dist-info/METADATA
trina_extension-1.0.0.dist-info/WHEEL
trina_extension-1.0.0.dist-info/licenses/LICENCE.txt
trina_extension-1.0.0.dist-info/RECORD
