Metadata-Version: 2.1
Name: trina_extension
Version: 1.0.0
Summary: A python package to indentify the type of a given file
Author-email: Trina Mukherjee <trina49607@gmail.com>
License-File: LICENCE.txt
Classifier: License :: OSI Approved :: MIT License
Classifier: Operating System :: OS Independent
Classifier: Programming Language :: Python :: 3
Requires-Python: >=3.7
